swordie_db
