Metadata-Version: 1.1
Name: swordiedb
Version: 0.2.0
Summary: A database API for SwordieMS-based maplestory sources.
Home-page: UNKNOWN
Author: Brandon Nguyen
Author-email: brandonnguyen3301@gmail.com
License: MIT
Keywords: database,swordie,maplestory
Platform: UNKNOWN
Classifier: Development Status :: 2 - Pre-Alpha
Classifier: Intended Audience :: Education
Classifier: Operating System :: Microsoft :: Windows :: Windows 10
Classifier: License :: OSI Approved :: MIT License
Classifier: Programming Language :: Python :: 3
